LaTeX_PyPi/LaTeX_img_tab.py
LaTeX_PyPi/__init__.py
LaTeX_PyPi-0.3.dist-info/METADATA
LaTeX_PyPi-0.3.dist-info/WHEEL
LaTeX_PyPi-0.3.dist-info/top_level.txt
LaTeX_PyPi-0.3.dist-info/RECORD
