Metadata-Version: 2.1
Name: LaTeX_PyPi
Version: 0.3
Summary: This is the simplest module for working with tables and images in LaTeX
Author: puzyriok
Author-email: sacrumterra@yandex.ru
Requires-Python: >=3.8
